codificatore_di_priorità/cdp_sync.v
module cdp_sync(input [3:0] in, output reg [1:0] out, input wire clk, output reg valid);
    always @(posedge clk) begin
        valid = 1'b1;
        casez(in)
            4'b1???: out = 2'b00;   //priorità al bit più significativo
            4'b01??: out = 2'b01;   //se il bit più significativo è 0, controlla il successivo
            4'b001?: out = 2'b10;   //se i primi due bit sono 0, controlla il terzo
            4'b0001: out = 2'b11;   //se i primi tre bit sono 0, l'ultimo è 1
            default: begin  //caso in cui tutti i bit sono 0
                out = 2'b00;
                valid = 1'b0;
            end
        endcase
    end
endmodule

codificatore_di_priorità/cdp_async.v
module cdp_async(input [3:0] in, output reg [1:0] out, output reg valid);
    always @(*) begin //aggiorna l'uscita ad ogni cambiamento dell'ingresso
        valid = 1'b1; //bit di validità
        casez(in) //switch con facoltà di ignorare l'alta impedenza
            4'b1???: out = 2'b00;   //priorità al bit più significativo
            4'b01??: out = 2'b01;   //se il bit più significativo è 0, controlla il successivo
            4'b001?: out = 2'b10;   //se i primi due bit sono 0, controlla il terzo
            4'b0001: out = 2'b11;   //se i primi tre bit sono 0, l'ultimo è 1
            default: begin  //caso in cui tutti i bit sono 0
                out = 2'b00;
                valid = 1'b0;
            end
        endcase
    end
endmodule

codificatore_di_priorità/testbench.v
module testbench();
    reg [3:0] in;
    wire [1:0] out_async, out_sync;
    wire valid_async, valid_sync;
    reg clk;

    cdp_async UUT_async (in, out_async, valid_async);
    cdp_sync UUT_sync (in, out_sync, clk, valid_sync);


//Blocco di gestione del clock
    initial begin
        clk = 0;  // Inizializza il clock a 0
    end

    always #5 clk = ~clk;  // Genera clock con periodo 10 unità di tempo


    initial begin
        $dumpfile("testbench.vcd");
        $dumpvars(0, testbench);

        // Test case 1: Input 4'b1000
        in = 4'b1000;
        #10; // Wait for 10 time units (1 ciclo di clock)
        $display("Input: %b, Async Output: %b, Async Valid: %b, Sync Output: %b, Sync Valid: %b", in, out_async, valid_async, out_sync, valid_sync);

        // Test case 2: Input 4'b0100
        in = 4'b0100;
        #10; // Wait for 10 time units
        $display("Input: %b, Async Output: %b, Async Valid: %b, Sync Output: %b, Sync Valid: %b", in, out_async, valid_async, out_sync, valid_sync);

        // Test case 3: Input 4'b0010
        in = 4'b0010;
        #10; // Wait for 10 time units
        $display("Input: %b, Async Output: %b, Async Valid: %b, Sync Output: %b, Sync Valid: %b", in, out_async, valid_async, out_sync, valid_sync);

        // Test case 4: Input 4'b0001
        in = 4'b0001;
        #10; // Wait for 10 time units
        $display("Input: %b, Async Output: %b, Async Valid: %b, Sync Output: %b, Sync Valid: %b", in, out_async, valid_async, out_sync, valid_sync);

        // Test case 5: Input 4'b0000 (no valid input)
        in = 4'b0000;
        #10; // Wait for 10 time units
        $display("Input: %b, Async Output: %b, Async Valid: %b, Sync Output: %b, Sync Valid: %b", in, out_async, valid_async, out_sync, valid_sync);

        // Test case 6: Input with multiple high bits (e.g., 4'b1100)
        in = 4'b1100;
        #10; // Wait for 10 time units
        $display("Input: %b, Async Output: %b, Async Valid: %b, Sync Output: %b, Sync Valid: %b", in, out_async, valid_async, out_sync, valid_sync);

        // End simulation
        $finish;
    end
endmodule

codificatore_di_priorità/testbench.vcd
$date
	Thu Oct 16 19:58:54 2025
$end
$version
	Icarus Verilog
$end
$timescale
	1s
$end
$scope module testbench $end
$var wire 1 ! valid_sync $end
$var wire 1 " valid_async $end
$var wire 2 # out_sync [1:0] $end
$var wire 2 $ out_async [1:0] $end
$var reg 1 % clk $end
$var reg 4 & in [3:0] $end
$scope module UUT_async $end
$var wire 4 ' in [3:0] $end
$var reg 2 ( out [1:0] $end
$var reg 1 " valid $end
$upscope $end
$scope module UUT_sync $end
$var wire 1 % clk $end
$var wire 4 ) in [3:0] $end
$var reg 2 * out [1:0] $end
$var reg 1 ! valid $end
$upscope $end
$upscope $end
$enddefinitions $end
#0
$dumpvars
bx *
b1000 )
b0 (
b1000 '
b1000 &
0%
b0 $
bx #
1"
x!
$end
#5
b0 #
b0 *
1!
1%
#10
b1 $
b1 (
0%
b100 &
b100 '
b100 )
#15
b1 #
b1 *
1%
#20
b10 $
b10 (
0%
b10 &
b10 '
b10 )
#25
b10 #
b10 *
1%
#30
b11 $
b11 (
0%
b1 &
b1 '
b1 )
#35
b11 #
b11 *
1%
#40
0"
b0 $
b0 (
0%
b0 &
b0 '
b0 )
#45
0!
b0 #
b0 *
1%
#50
1"
0%
b1100 &
b1100 '
b1100 )
#55
1!
1%
