101_sequence_detector/sequence_detector.v
module sequence_detector(input wire clk, input wire in_bit, input wire reset, output reg found);
    parameter s0 = 2'b00; 
    parameter s1 = 2'b01;
    parameter s2 = 2'b10;

    reg [1:0] state, next_state;

    always @(posedge clk or posedge reset) begin
        if(reset) begin
            state<=s0;
        end
        else
        begin 
            state<=next_state;
        end
    end

    always @(*) begin 
        found=0; 
        case(state)
            s0 : next_state = in_bit ? s1 : s0;
            s1 : next_state = in_bit ? s1 : s2;
            s2 : begin 
                next_state = in_bit ? s1 : s0 ;
                if(in_bit==1'b1) begin 
                    found = 1; 
                end
            end
        default : next_state=s0;
    endcase
    end
endmodule

101_sequence_detector/testbench.v
module tb_sequence_detector();

    // segnali del testbench
    reg clk = 0;
    reg reset;
    reg in_bit;
    wire found;

    // istanza del modulo sotto test
    sequence_detector uut (
        .clk(clk),
        .in_bit(in_bit),
        .reset(reset),
        .found(found)
    );

    // generatore di clock: periodo 10 unità di tempo
    always #5 clk = ~clk;

    initial begin
        // Dump dei segnali per VCD (per simulazione con waveform)
        $dumpfile("sequence_detector.vcd");
        $dumpvars(0, tb_sequence_detector);

        // inizializzazione
        reset = 1;
        in_bit = 0;
        #10 reset = 0;  // fine reset

        // Flusso di test: esempio con sequenze 101
        // sequenza: 1 0 1 0 1 1 0 1
        in_bit = 1; #10;
        in_bit = 0; #10;
        in_bit = 1; #10;  // qui found dovrebbe diventare 1
        in_bit = 0; #10;
        in_bit = 1; #10;  // qui found di nuovo 1
        in_bit = 1; #10;
        in_bit = 0; #10;
        in_bit = 1; #10;  // found ancora 1

        // fine simulazione
        #20 $finish;
    end

endmodule

101_sequence_detector/sequence_detector.vcd
$date
	Thu Oct 16 22:47:56 2025
$end
$version
	Icarus Verilog
$end
$timescale
	1s
$end
$scope module tb_sequence_detector $end
$var wire 1 ! found $end
$var reg 1 " clk $end
$var reg 1 # in_bit $end
$var reg 1 $ reset $end
$scope module uut $end
$var wire 1 " clk $end
$var wire 1 # in_bit $end
$var wire 1 $ reset $end
$var reg 1 ! found $end
$var reg 2 % next_state [1:0] $end
$var reg 2 & state [1:0] $end
$upscope $end
$upscope $end
$enddefinitions $end
#0
$dumpvars
b0 &
b0 %
1$
0#
0"
0!
$end
#5
1"
#10
b1 %
0"
1#
0$
#15
b1 &
1"
#20
b10 %
0"
0#
#25
b0 %
b10 &
1"
#30
1!
b1 %
0"
1#
#35
0!
b1 &
1"
#40
b10 %
0"
0#
#45
b0 %
b10 &
1"
#50
1!
b1 %
0"
1#
#55
0!
b1 &
1"
#60
0"
#65
1"
#70
b10 %
0"
0#
#75
b0 %
b10 &
1"
#80
1!
b1 %
0"
1#
#85
0!
b1 &
1"
