counter_mod8/synth_counter_mod8.v
/* Generated by Yosys 0.33 (git sha1 2584903a060) */

(* src = "/mnt/c/Users/ruozz/OneDrive/Desktop/uni/arch2/VERILOG/primi_es/counter_mod8/counter.v:1.1-15.10" *)
module counter_mod8(clk, reset, enable, count);
  wire _00_;
  wire _01_;
  wire _02_;
  wire _03_;
  wire _04_;
  (* src = "/mnt/c/Users/ruozz/OneDrive/Desktop/uni/arch2/VERILOG/primi_es/counter_mod8/counter.v:1.32-1.35" *)
  input clk;
  wire clk;
  (* src = "/mnt/c/Users/ruozz/OneDrive/Desktop/uni/arch2/VERILOG/primi_es/counter_mod8/counter.v:1.91-1.96" *)
  output [2:0] count;
  reg [2:0] count;
  (* src = "/mnt/c/Users/ruozz/OneDrive/Desktop/uni/arch2/VERILOG/primi_es/counter_mod8/counter.v:1.66-1.72" *)
  input enable;
  wire enable;
  (* src = "/mnt/c/Users/ruozz/OneDrive/Desktop/uni/arch2/VERILOG/primi_es/counter_mod8/counter.v:1.48-1.53" *)
  input reset;
  wire reset;
  assign _00_ = count[0] & count[1];
  assign _01_ = ~(_00_ & count[2]);
  assign _02_ = _01_ & ~(count[0]);
  assign _03_ = count[0] ^ count[1];
  assign _04_ = _00_ ^ count[2];
  (* src = "/mnt/c/Users/ruozz/OneDrive/Desktop/uni/arch2/VERILOG/primi_es/counter_mod8/counter.v:2.5-14.8" *)
  always @(posedge clk, posedge reset)
    if (reset) count[0] <= 1'h0;
    else if (enable) count[0] <= _02_;
  (* src = "/mnt/c/Users/ruozz/OneDrive/Desktop/uni/arch2/VERILOG/primi_es/counter_mod8/counter.v:2.5-14.8" *)
  always @(posedge clk, posedge reset)
    if (reset) count[1] <= 1'h0;
    else if (enable) count[1] <= _03_;
  (* src = "/mnt/c/Users/ruozz/OneDrive/Desktop/uni/arch2/VERILOG/primi_es/counter_mod8/counter.v:2.5-14.8" *)
  always @(posedge clk, posedge reset)
    if (reset) count[2] <= 1'h0;
    else if (enable) count[2] <= _04_;
endmodule

counter_mod8/testbench.v
module tb_counter_mod8;
    reg clk = 0;
    reg reset; //si usa reg per i segnali generati e wire per quelli ricevuti
    reg enable;
    wire [2:0] count;

    // istanza del modulo
    counter_mod8 uut (
        .clk(clk),
        .reset(reset),
        .enable(enable),
        .count(count) //.nome_nel_modulo(nome_nel_testbench)
    );

    // generatore di clock
    always #5 clk = ~clk; //clock invertito ogni 5 unità di tempo

    initial begin
        $dumpfile("waveform.vcd");
        $dumpvars(0,tb_counter_mod8);
        reset = 1;
        enable = 0;
        #10 reset = 0;
        enable = 1;

        #100 $finish; // fine simulazione
    end
endmodule

counter_mod8/waveform.vcd
$date
	Thu Oct 16 21:38:21 2025
$end
$version
	Icarus Verilog
$end
$timescale
	1s
$end
$scope module tb_counter_mod8 $end
$var wire 3 ! count [2:0] $end
$var reg 1 " clk $end
$var reg 1 # enable $end
$var reg 1 $ reset $end
$scope module uut $end
$var wire 1 " clk $end
$var wire 1 # enable $end
$var wire 1 $ reset $end
$var reg 3 % count [2:0] $end
$upscope $end
$upscope $end
$enddefinitions $end
#0
$dumpvars
b0 %
1$
0#
0"
b0 !
$end
#5
1"
#10
0"
1#
0$
#15
b1 !
b1 %
1"
#20
0"
#25
b10 !
b10 %
1"
#30
0"
#35
b11 !
b11 %
1"
#40
0"
#45
b100 !
b100 %
1"
#50
0"
#55
b101 !
b101 %
1"
#60
0"
#65
b110 !
b110 %
1"
#70
0"
#75
b111 !
b111 %
1"
#80
0"
#85
b0 !
b0 %
1"
#90
0"
#95
b1 !
b1 %
1"
#100
0"
#105
b10 !
b10 %
1"
