contatore_up_down/synth_counter_ud.v
/* Generated by Yosys 0.33 (git sha1 2584903a060) */

(* src = "/mnt/c/Users/ruozz/OneDrive/Desktop/uni/arch2/VERILOG/primi_es/contatore_up_down/contatore.v:1.1-14.10" *)
module contatore(clk, reset, enable, up_down, data_out);
  wire _00_;
  wire _01_;
  wire _02_;
  wire _03_;
  wire _04_;
  wire _05_;
  wire _06_;
  wire _07_;
  wire _08_;
  (* force_downto = 32'd1 *)
  (* src = "/mnt/c/Users/ruozz/OneDrive/Desktop/uni/arch2/VERILOG/primi_es/contatore_up_down/contatore.v:8.27-8.40|/usr/bin/../share/yosys/techmap.v:270.23-270.24" *)
  (* unused_bits = "1 2 3" *)
  wire [3:0] _09_;
  (* force_downto = 32'd1 *)
  (* src = "/mnt/c/Users/ruozz/OneDrive/Desktop/uni/arch2/VERILOG/primi_es/contatore_up_down/contatore.v:8.27-8.40|/usr/bin/../share/yosys/techmap.v:270.26-270.27" *)
  wire [3:0] _10_;
  (* src = "/mnt/c/Users/ruozz/OneDrive/Desktop/uni/arch2/VERILOG/primi_es/contatore_up_down/contatore.v:1.29-1.32" *)
  input clk;
  wire clk;
  (* src = "/mnt/c/Users/ruozz/OneDrive/Desktop/uni/arch2/VERILOG/primi_es/contatore_up_down/contatore.v:1.108-1.116" *)
  output [3:0] data_out;
  reg [3:0] data_out;
  (* src = "/mnt/c/Users/ruozz/OneDrive/Desktop/uni/arch2/VERILOG/primi_es/contatore_up_down/contatore.v:1.63-1.69" *)
  input enable;
  wire enable;
  (* src = "/mnt/c/Users/ruozz/OneDrive/Desktop/uni/arch2/VERILOG/primi_es/contatore_up_down/contatore.v:1.45-1.50" *)
  input reset;
  wire reset;
  (* src = "/mnt/c/Users/ruozz/OneDrive/Desktop/uni/arch2/VERILOG/primi_es/contatore_up_down/contatore.v:1.82-1.89" *)
  input up_down;
  wire up_down;
  assign _09_[0] = ~data_out[0];
  assign _00_ = data_out[1] ^ up_down;
  assign _10_[1] = _00_ ^ _09_[0];
  assign _01_ = ~(data_out[2] ^ up_down);
  assign _02_ = up_down | ~(data_out[1]);
  assign _03_ = data_out[0] & ~(_00_);
  assign _04_ = _02_ & ~(_03_);
  assign _10_[2] = ~(_04_ ^ _01_);
  assign _05_ = data_out[3] ^ up_down;
  assign _06_ = up_down | ~(data_out[2]);
  assign _07_ = _01_ & ~(_04_);
  assign _08_ = _06_ & ~(_07_);
  assign _10_[3] = _08_ ^ _05_;
  (* src = "/mnt/c/Users/ruozz/OneDrive/Desktop/uni/arch2/VERILOG/primi_es/contatore_up_down/contatore.v:2.5-13.8" *)
  always @(posedge clk, posedge reset)
    if (reset) data_out[0] <= 1'h0;
    else if (enable) data_out[0] <= _09_[0];
  (* src = "/mnt/c/Users/ruozz/OneDrive/Desktop/uni/arch2/VERILOG/primi_es/contatore_up_down/contatore.v:2.5-13.8" *)
  always @(posedge clk, posedge reset)
    if (reset) data_out[1] <= 1'h0;
    else if (enable) data_out[1] <= _10_[1];
  (* src = "/mnt/c/Users/ruozz/OneDrive/Desktop/uni/arch2/VERILOG/primi_es/contatore_up_down/contatore.v:2.5-13.8" *)
  always @(posedge clk, posedge reset)
    if (reset) data_out[2] <= 1'h0;
    else if (enable) data_out[2] <= _10_[2];
  (* src = "/mnt/c/Users/ruozz/OneDrive/Desktop/uni/arch2/VERILOG/primi_es/contatore_up_down/contatore.v:2.5-13.8" *)
  always @(posedge clk, posedge reset)
    if (reset) data_out[3] <= 1'h0;
    else if (enable) data_out[3] <= _10_[3];
  assign _10_[0] = _09_[0];
endmodule

contatore_up_down/testbench.v
`timescale 1ns/1ps

module tb_contatore;

    // segnali di test
    reg clk;
    reg reset;
    reg enable;
    reg up_down;
    wire [3:0] data_out;

    // istanza del modulo da testare
    contatore uut (
        .clk(clk),
        .reset(reset),
        .enable(enable),
        .up_down(up_down),
        .data_out(data_out)
    );

    // generatore di clock: periodo = 10 ns
    always #5 clk = ~clk;

    // blocco di stimolo
    initial begin
        // file per waveform
        $dumpfile("contatore.vcd");
        $dumpvars(0, tb_contatore);

        // inizializzazione
        clk = 0;
        reset = 1;
        enable = 0;
        up_down = 1;
        #10 reset = 0;  // rilascia il reset

        // inizio conteggio in su
        enable = 1;
        up_down = 1;
        #100; // aspetta un po' di clock

        // pausa
        enable = 0;
        #30;

        // conteggio in giù
        enable = 1;
        up_down = 0;
        #100;

        // fine simulazione
        $finish;
    end

endmodule

contatore_up_down/contatore.vcd
$date
	Fri Oct 17 02:00:39 2025
$end
$version
	Icarus Verilog
$end
$timescale
	1ps
$end
$scope module tb_contatore $end
$var wire 4 ! data_out [3:0] $end
$var reg 1 " clk $end
$var reg 1 # enable $end
$var reg 1 $ reset $end
$var reg 1 % up_down $end
$scope module uut $end
$var wire 1 " clk $end
$var wire 1 # enable $end
$var wire 1 $ reset $end
$var wire 1 % up_down $end
$var reg 4 & data_out [3:0] $end
$upscope $end
$upscope $end
$enddefinitions $end
#0
$dumpvars
b0 &
1%
1$
0#
0"
b0 !
$end
#5000
1"
#10000
0"
1#
0$
#15000
b1 !
b1 &
1"
#20000
0"
#25000
b10 !
b10 &
1"
#30000
0"
#35000
b11 !
b11 &
1"
#40000
0"
#45000
b100 !
b100 &
1"
#50000
0"
#55000
b101 !
b101 &
1"
#60000
0"
#65000
b110 !
b110 &
1"
#70000
0"
#75000
b111 !
b111 &
1"
#80000
0"
#85000
b1000 !
b1000 &
1"
#90000
0"
#95000
b1001 !
b1001 &
1"
#100000
0"
#105000
b1010 !
b1010 &
1"
#110000
0"
0#
#115000
1"
#120000
0"
#125000
1"
#130000
0"
#135000
1"
#140000
0"
0%
1#
#145000
b1001 !
b1001 &
1"
#150000
0"
#155000
b1000 !
b1000 &
1"
#160000
0"
#165000
b111 !
b111 &
1"
#170000
0"
#175000
b110 !
b110 &
1"
#180000
0"
#185000
b101 !
b101 &
1"
#190000
0"
#195000
b100 !
b100 &
1"
#200000
0"
#205000
b11 !
b11 &
1"
#210000
0"
#215000
b10 !
b10 &
1"
#220000
0"
#225000
b1 !
b1 &
1"
#230000
0"
#235000
b0 !
b0 &
1"
