comparatore/comparatore.v
module comparatore(input A, input B, output GT, output EQ, output LT);
assign GT = A & ~B; 
/*
0 0 -> 0
0 1 -> 0
1 1 -> 0
1 0 -> 1
quindi l'espressione fa quello che fa l'operazione di confronto "maggiore di" */
assign EQ = ~(A ^ B); 
/*
0 0 -> 1
0 1 -> 0
1 0 -> 0
1 1 -> 1 */
assign LT = ~A & B;
/*
speculare a quello che abbiamo fatto per GT
*/
endmodule

comparatore/comparatore4.v
module comparatore4(input [3:0] A, input [3:0] B, output GT, output EQ, output LT);
wire GT1, EQ1, LT1;
wire GT2, EQ2, LT2;
wire GT3, EQ3, LT3;
wire GT4, EQ4, LT4;
comparatore C1(A[3], B[3], GT1, EQ1, LT1);
comparatore C2(A[2], B[2], GT2, EQ2, LT2);
comparatore C3(A[1], B[1], GT3, EQ3, LT3);
comparatore C4(A[0], B[0], GT4, EQ4, LT4);
assign GT = GT1 | (EQ1 & GT2) | (EQ1 & EQ2 & GT3) | (EQ1 & EQ2 & EQ3 & GT4);
/*
- se il primo bit è maggiore imposta su 1 GT
- se il primo bit è uguale , ma il secondo è maggiore imposta su 1 GT
- ... 
*/
assign EQ = EQ1 & EQ2 & EQ3 & EQ4;
/*
tutti i bit devono essere uguali 
*/
assign LT = LT1 | (EQ1 & LT2) | (EQ1 & EQ2 & LT3) | (EQ1 & EQ2 & EQ3 & LT4);
/*
- se il primo bit è inferiore imposta su 1 LT
- se il primo bit è uguale, ma il secondo è minore imposta su 1 LT
- ... 
*/
endmodule

comparatore/testbench.v
module testbench();
    reg [3:0] A;
    reg [3:0] B;
    wire GT, EQ, LT;
    comparatore4 C(A, B, GT, EQ, LT);
    initial begin
        $dumpfile("waveform.vcd");
        $dumpvars(0, testbench);
        A = 4'b0000; B = 4'b0000; #10;
        A = 4'b0000; B = 4'b0001; #10;
        A = 4'b0001; B = 4'b0000; #10;
        A = 4'b0010; B = 4'b0001; #10;
        A = 4'b0010; B = 4'b0010; #10;
        A = 4'b0010; B = 4'b0011; #10;
        A = 4'b1111; B = 4'b1111; #10;
        A = 4'b1111; B = 4'b1110; #10;
        A = 4'b1110; B = 4'b1111; #10;
        $stop;
    end
endmodule

comparatore/waveform.vcd
$date
	Thu Oct 16 14:30:39 2025
$end
$version
	Icarus Verilog
$end
$timescale
	1s
$end
$scope module testbench $end
$var wire 1 ! LT $end
$var wire 1 " GT $end
$var wire 1 # EQ $end
$var reg 4 $ A [3:0] $end
$var reg 4 % B [3:0] $end
$scope module C $end
$var wire 4 & A [3:0] $end
$var wire 4 ' B [3:0] $end
$var wire 1 # EQ $end
$var wire 1 " GT $end
$var wire 1 ! LT $end
$var wire 1 ( LT4 $end
$var wire 1 ) LT3 $end
$var wire 1 * LT2 $end
$var wire 1 + LT1 $end
$var wire 1 , GT4 $end
$var wire 1 - GT3 $end
$var wire 1 . GT2 $end
$var wire 1 / GT1 $end
$var wire 1 0 EQ4 $end
$var wire 1 1 EQ3 $end
$var wire 1 2 EQ2 $end
$var wire 1 3 EQ1 $end
$scope module C1 $end
$var wire 1 4 A $end
$var wire 1 5 B $end
$var wire 1 3 EQ $end
$var wire 1 / GT $end
$var wire 1 + LT $end
$upscope $end
$scope module C2 $end
$var wire 1 6 A $end
$var wire 1 7 B $end
$var wire 1 2 EQ $end
$var wire 1 . GT $end
$var wire 1 * LT $end
$upscope $end
$scope module C3 $end
$var wire 1 8 A $end
$var wire 1 9 B $end
$var wire 1 1 EQ $end
$var wire 1 - GT $end
$var wire 1 ) LT $end
$upscope $end
$scope module C4 $end
$var wire 1 : A $end
$var wire 1 ; B $end
$var wire 1 0 EQ $end
$var wire 1 , GT $end
$var wire 1 ( LT $end
$upscope $end
$upscope $end
$upscope $end
$enddefinitions $end
#0
$dumpvars
0;
0:
09
08
07
06
05
04
13
12
11
10
0/
0.
0-
0,
0+
0*
0)
0(
b0 '
b0 &
b0 %
b0 $
1#
0"
0!
$end
#10
0#
1!
00
1(
1;
b1 %
b1 '
#20
1"
0!
1,
0(
0;
1:
b0 %
b0 '
b1 $
b1 &
#30
0!
1"
01
1(
1-
0,
1;
18
0:
b1 %
b1 '
b10 $
b10 &
#40
0"
1#
0-
11
10
0(
19
0;
b10 %
b10 '
#50
0#
1!
00
1(
1;
b11 %
b11 '
#60
0"
0!
1#
10
0(
0/
0.
15
17
14
16
1:
b1111 %
b1111 '
b1111 $
b1111 &
#70
1"
0#
1,
00
0;
b1110 %
b1110 '
#80
1!
0"
1(
0,
1;
0:
b1111 %
b1111 '
b1110 $
b1110 &
